fastshield/__init__.py
fastshield/fshield.py
fastshield/middleware.py
fastshield/request.py
fastshield/classifire/__init__.py
fastshield/classifire/classifire.py
fastshield/exceptions/__init__.py
fastshield/exceptions/hackexceptions.py
fastshield/models/predictor.joblib
fastshield/models/pt_predictor.joblib
fastshield-0.0.5.dist-info/LICENSE
fastshield-0.0.5.dist-info/METADATA
fastshield-0.0.5.dist-info/WHEEL
fastshield-0.0.5.dist-info/top_level.txt
fastshield-0.0.5.dist-info/RECORD
