Metadata-Version: 2.1
Name: fastshield
Version: 0.0.5
Summary: library to protect your fastapi applications
Home-page: https://github.com/knyazevi81/fastshield
Author: ilpdakz
Author-email: khasanknyazev81@gmail.com
Project-URL: GitHub, https://github.com/knyazevi81
Keywords: files speedfiles
Classifier: Programming Language :: Python :: 3.11
Classifier: License :: OSI Approved :: MIT License
Classifier: Operating System :: OS Independent
Requires-Python: >=3.6
License-File: LICENSE
Requires-Dist: requests>=2.25.1
Requires-Dist: scikit-learn==1.5.1
